pyteams_msg/__about__.py
pyteams_msg/__init__.py
pyteams_msg/adaptivecard.py
pyteams_msg/teamsmessage.py
pyteams_msg/sections/__init__.py
pyteams_msg/sections/image.py
pyteams_msg/sections/section.py
pyteams_msg/sections/textblock.py
pyteams_msg-0.0.2.dist-info/LICENSE
pyteams_msg-0.0.2.dist-info/METADATA
pyteams_msg-0.0.2.dist-info/WHEEL
pyteams_msg-0.0.2.dist-info/top_level.txt
pyteams_msg-0.0.2.dist-info/RECORD
