Metadata-Version: 2.1
Name: pyteams-msg
Version: 0.0.2
Summary: Build and post messages to Microsoft Teams
Home-page: https://github.com/jmillana/pyteams_msg
Author: Jordi Marimon
Author-email: jordi@marimon.tech
Project-URL: Bug Tracker, https://github.com/jmillana/pyteams_msg/issues
Classifier: Programming Language :: Python :: 3
Classifier: License :: OSI Approved :: GNU General Public License v3 (GPLv3)
Classifier: Operating System :: OS Independent
Requires-Python: >=3.6
License-File: LICENSE
